SettleSheet.py
settlesheet-1.0.0.dist-info/METADATA
settlesheet-1.0.0.dist-info/WHEEL
settlesheet-1.0.0.dist-info/entry_points.txt
settlesheet-1.0.0.dist-info/top_level.txt
settlesheet-1.0.0.dist-info/RECORD
