Metadata-Version: 2.4
Name: settlesheet
Version: 1.0.0
Summary: Spreadsheet-based group expense tracker and settlement generator.
Author: Phil Cigan
License: CC-BY-SA-4.0
Project-URL: Homepage, https://github.com/pjcigan/settlesheet
Project-URL: Repository, https://github.com/pjcigan/settlesheet
Project-URL: Issues, https://github.com/pjcigan/settlesheet/issues
Classifier: Programming Language :: Python :: 3
Classifier: License :: Other/Proprietary License
Classifier: Operating System :: OS Independent
Classifier: Topic :: Office/Business :: Financial :: Accounting
Classifier: Development Status :: 5 - Production/Stable
Requires-Python: >=3.7
Requires-Dist: openpyxl>=3.0.0
